COPYRIGHT
MANIFEST.in
Makefile
README
setup.py
test/__init__.py
test/__init__.pyc
test/test_compile.py
test/test_simple.py
test/__pycache__/test_compile.cpython-27-PYTEST.pyc
test/__pycache__/test_simple.cpython-27-PYTEST.pyc
tiddlywebplugins/__init__.py
tiddlywebplugins/hashmaker.py
tiddlywebplugins.hashmaker.egg-info/PKG-INFO
tiddlywebplugins.hashmaker.egg-info/SOURCES.txt
tiddlywebplugins.hashmaker.egg-info/dependency_links.txt
tiddlywebplugins.hashmaker.egg-info/namespace_packages.txt
tiddlywebplugins.hashmaker.egg-info/not-zip-safe
tiddlywebplugins.hashmaker.egg-info/requires.txt
tiddlywebplugins.hashmaker.egg-info/top_level.txt