Metadata-Version: 1.0
Name: tiddlywebplugins.hashmaker
Version: 0.9
Summary: Add a hash digest field to tiddlers
Home-page: http://pypi.python.org/pypi/tiddlywebplugins.hashmaker
Author: Chris Dent
Author-email: cdent@peermore.com
License: BSD
Platform: Posix; MacOS X; Windows
